waveome/__init__.py
waveome/kernels.py
waveome/likelihoods.py
waveome/model_classes.py
waveome/model_fitting.py
waveome/model_search.py
waveome/model_types_DEPR.py
waveome/predictions.py
waveome/regularization.py
waveome/utilities.py
waveome-0.1.1.dist-info/licenses/LICENSE
waveome-0.1.1.dist-info/METADATA
waveome-0.1.1.dist-info/WHEEL
waveome-0.1.1.dist-info/top_level.txt
waveome-0.1.1.dist-info/RECORD
