Metadata-Version: 2.4
Name: waveome
Version: 0.1.1
Summary: Automated longitudinal data analysis using Gaussian processes.
Home-page: https://github.com/omicsEye/waveome
Author: Allen Ross
Author-email: Allen Ross <allenross@gwu.edu>
License: MIT
Project-URL: Homepage, https://github.com/omicsEye/waveome
Project-URL: Bug Tracker, https://github.com/omicsEye/waveome/issues
Classifier: Development Status :: 3 - Alpha
Classifier: Intended Audience :: Science/Research
Classifier: License :: OSI Approved :: MIT License
Classifier: Programming Language :: Python :: 3
Classifier: Programming Language :: Python :: 3.9
Classifier: Programming Language :: Python :: 3.10
Classifier: Programming Language :: Python :: 3.11
Classifier: Topic :: Scientific/Engineering :: Bio-Informatics
Classifier: Topic :: Scientific/Engineering :: Artificial Intelligence
Classifier: Operating System :: OS Independent
Requires-Python: >=3.9,<3.12
License-File: LICENSE
Requires-Dist: tensorflow<2.16.0,>=2.12.0
Requires-Dist: tensorflow_probability<0.24.0,>=0.20.0
Requires-Dist: gpflow==2.9.1
Requires-Dist: pandas>=2.0.0
Requires-Dist: numpy>=1.24.0
Requires-Dist: ray[default]
Requires-Dist: scipy>=1.11.0
Requires-Dist: joblib
Requires-Dist: seaborn
Requires-Dist: matplotlib
Requires-Dist: tqdm
Requires-Dist: setuptools<66.0.0,>=65.5.1
Requires-Dist: psutil
Dynamic: author
Dynamic: home-page
Dynamic: license-file
Dynamic: requires-python
